{
  "type": "infinity_nexus_mod:assembler",
  "duration": 1500,
  "energy": 1000,
  "ingredients": [
    {
      "item": "infinity_nexus_mod:reinforced_component"
    },
    {
      "item": "infinity_nexus_mod:tin_rod"
    },
    {
      "item": "infinity_nexus_mod:tin_screw"
    },
    {
      "item": "infinity_nexus_mod:tin_rod"
    },
    {
      "item": "infinity_nexus_mod:tin_sheet"
    },
    {
      "item": "infinity_nexus_mod:tin_sheet"
    },
    {
      "item": "infinity_nexus_mod:tin_rod"
    },
    {
      "item": "infinity_nexus_mod:tin_screw"
    },
    {
      "item": "infinity_nexus_mod:tin_rod"
    }
  ],
  "output": {
    "item": "infinity_nexus_mod:tin_machine_casing",
    "count": 1
  }
}